MANIFEST.in
README.md
requirements.txt
setup.py
jerry/__init__.py
jerry/main.py
jerry/utils.py
jerry/attacks/__init__.py
jerry/attacks/dump.py
jerry/attacks/executeCommands.py
jerry/attacks/scanNetwork.py
jerry/attacks/sys_infos.py
jerry/attacks/systemInfo.py
jerry/attacks/bruteforce/__init__.py
jerry/attacks/bruteforce/bruteforce.py
saes6_jerry.egg-info/PKG-INFO
saes6_jerry.egg-info/SOURCES.txt
saes6_jerry.egg-info/dependency_links.txt
saes6_jerry.egg-info/entry_points.txt
saes6_jerry.egg-info/requires.txt
saes6_jerry.egg-info/top_level.txt